ml_project_initializer/__init__.py
ml_project_initializer/cli.py
init_ml_app-0.1.0.dist-info/METADATA
init_ml_app-0.1.0.dist-info/WHEEL
init_ml_app-0.1.0.dist-info/entry_points.txt
init_ml_app-0.1.0.dist-info/top_level.txt
init_ml_app-0.1.0.dist-info/RECORD
